qian/__init__.py
qian-0.1.3.dist-info/LICENSE
qian-0.1.3.dist-info/METADATA
qian-0.1.3.dist-info/WHEEL
qian-0.1.3.dist-info/top_level.txt
qian-0.1.3.dist-info/RECORD
