Metadata-Version: 2.1
Name: qian
Version: 0.1.3
Summary: Quantitative Investment Algorithm Nexus
Home-page: https://github.com/qiancapital/qian
Author: Samson Qian
Author-email: samsonqian@gmail.com
License: MIT
Keywords: quantitative-research time-series value-investing business-analysis valuation cash-flow
Requires-Python: >=3.6
License-File: LICENSE
